SonOyuncuSiralamaApi/__init__.py
SonOyuncuSiralamaApi/main.py
SonOyuncuSiralamaApi-0.1.dist-info/METADATA
SonOyuncuSiralamaApi-0.1.dist-info/WHEEL
SonOyuncuSiralamaApi-0.1.dist-info/top_level.txt
SonOyuncuSiralamaApi-0.1.dist-info/RECORD
