Metadata-Version: 2.1
Name: SonOyuncuSiralamaApi
Version: 0.1
Requires-Dist: requests
Requires-Dist: beautifulsoup4
